collada/__init__.py
collada/__main__.py
collada/animation.py
collada/asset.py
collada/camera.py
collada/common.py
collada/controller.py
collada/geometry.py
collada/light.py
collada/lineset.py
collada/material.py
collada/polygons.py
collada/polylist.py
collada/primitive.py
collada/scene.py
collada/schema.py
collada/source.py
collada/triangleset.py
collada/util.py
collada/xmlutil.py
collada/resources/__init__.py
collada/resources/schema-1.4.1.xml
collada/resources/xsd.xml
collada/tests/__init__.py
collada/tests/test_asset.py
collada/tests/test_camera.py
collada/tests/test_collada.py
collada/tests/test_geometry.py
collada/tests/test_ignore.py
collada/tests/test_iteration.py
collada/tests/test_light.py
collada/tests/test_lineset.py
collada/tests/test_material.py
collada/tests/test_scene.py
collada/tests/test_source.py
pycollada-0.9.1.dist-info/licenses/AUTHORS.md
pycollada-0.9.1.dist-info/licenses/COPYING
pycollada-0.9.1.dist-info/METADATA
pycollada-0.9.1.dist-info/WHEEL
pycollada-0.9.1.dist-info/top_level.txt
pycollada-0.9.1.dist-info/RECORD
