Metadata-Version: 2.4
Name: pycollada
Version: 0.9.1
Summary: python library for reading and writing collada documents
Author-email: Jeff Terrace and contributors <jterrace@gmail.com>
License: BSD
Project-URL: Homepage, http://pycollada.readthedocs.org/
Platform: any
License-File: COPYING
License-File: AUTHORS.md
Requires-Dist: python-dateutil
Requires-Dist: numpy
Provides-Extra: prettyprint
Requires-Dist: lxml; extra == "prettyprint"
Provides-Extra: validation
Requires-Dist: lxml; extra == "validation"
Dynamic: license-file
